pyaardvark/__init__.py
pyaardvark/aardvark.py
pyaardvark/cli_tool.py
pyaardvark/constants.py
pyaardvark/version.py
pyaardvark/ext/LICENSE.txt
pyaardvark/ext/__init__.py
pyaardvark/ext/linux32/__init__.py
pyaardvark/ext/linux32/aardvark.so
pyaardvark/ext/linux64/__init__.py
pyaardvark/ext/linux64/aardvark.so
pyaardvark/ext/linuxarm32/__init__.py
pyaardvark/ext/linuxarm32/aardvark.so
pyaardvark/ext/linuxarm64/__init__.py
pyaardvark/ext/linuxarm64/aardvark.so
pyaardvark/ext/osx64/__init__.py
pyaardvark/ext/osx64/aardvark.so
pyaardvark/ext/osxarm/__init__.py
pyaardvark/ext/osxarm/aardvark.so
pyaardvark/ext/win32/__init__.py
pyaardvark/ext/win32/aardvark.pyd
pyaardvark/ext/win64/__init__.py
pyaardvark/ext/win64/aardvark.pyd
pyaardvark/ext/winarm/__init__.py
pyaardvark/ext/winarm/aardvark.pyd
tests/__init__.py
tests/test_aardvark.py
tests/test_ext.py
pyaardvark-0.8.1.dist-info/AUTHORS
pyaardvark-0.8.1.dist-info/COPYING
pyaardvark-0.8.1.dist-info/METADATA
pyaardvark-0.8.1.dist-info/WHEEL
pyaardvark-0.8.1.dist-info/entry_points.txt
pyaardvark-0.8.1.dist-info/top_level.txt
pyaardvark-0.8.1.dist-info/RECORD
