Metadata-Version: 2.1
Name: pyaardvark
Version: 0.8.1
Summary: Total Phase Aardvark library
Home-page: http://github.com/kontron/python-aardvark
Author: Michael Walle
Author-email: michael.walle@kontron.com
License: LGPLv2+
Classifier: Development Status :: 3 - Alpha
Classifier: Environment :: Console
Classifier: License :: OSI Approved :: GNU Lesser General Public License v2 or later (LGPLv2+)
Classifier: Natural Language :: English
Classifier: Operating System :: OS Independent
Classifier: Programming Language :: Python :: 3
Classifier: Programming Language :: Python :: 3.9
Classifier: Programming Language :: Python :: 3.10
Classifier: Programming Language :: Python :: 3.11
Classifier: Programming Language :: Python :: 3.12
Classifier: Topic :: Software Development :: Libraries :: Python Modules
License-File: COPYING
License-File: AUTHORS
Requires-Dist: future
